qiskit_qir/__init__.py
qiskit_qir/capability.py
qiskit_qir/elements.py
qiskit_qir/translate.py
qiskit_qir/visitor.py
iqm_qiskit_qir-0.8.0.dist-info/LICENSE
iqm_qiskit_qir-0.8.0.dist-info/METADATA
iqm_qiskit_qir-0.8.0.dist-info/NOTICE.txt
iqm_qiskit_qir-0.8.0.dist-info/WHEEL
iqm_qiskit_qir-0.8.0.dist-info/top_level.txt
iqm_qiskit_qir-0.8.0.dist-info/RECORD
