Metadata-Version: 2.2
Name: iqm-qiskit-qir
Version: 0.8.0
Summary: Qiskit to QIR translator
Home-page: https://github.com/microsoft/qiskit-qir
Author: Microsoft
Author-email: que-contacts@microsoft.com
Project-URL: Bug Tracker, https://github.com/microsoft/qiskit-qir
Classifier: Development Status :: 3 - Alpha
Classifier: Intended Audience :: Developers
Classifier: License :: OSI Approved :: MIT License
Classifier: Natural Language :: English
Classifier: Programming Language :: Python :: 3
Classifier: Programming Language :: Python :: 3.8
Classifier: Programming Language :: Python :: 3.9
Classifier: Programming Language :: Python :: 3.10
Classifier: Programming Language :: Python :: 3.11
Classifier: Programming Language :: Python :: 3.12
Classifier: Operating System :: Microsoft
Classifier: Operating System :: MacOS
Classifier: Operating System :: Unix
Requires-Python: <3.13,>=3.8
License-File: LICENSE
License-File: NOTICE.txt
Requires-Dist: qiskit<2.0,>=1.0.0
Requires-Dist: iqm-pyqir==0.12.0
Provides-Extra: test
Requires-Dist: pytest; extra == "test"
